luma/__init__.py
luma/app/.deployignore
luma/app/.eslintrc.json
luma/app/.gitignore
luma/app/.prettierrc
luma/app/components/Breadcrumb.tsx
luma/app/components/Callout.module.css
luma/app/components/Callout.tsx
luma/app/components/CodeBlock.module.css
luma/app/components/CodeBlock.tsx
luma/app/components/CrossRef.tsx
luma/app/components/Footer.module.css
luma/app/components/Footer.tsx
luma/app/components/Heading.tsx
luma/app/components/SearchBar.module.css
luma/app/components/SearchBar.tsx
luma/app/components/SideNav.module.css
luma/app/components/SideNav.tsx
luma/app/components/TableOfContents.module.css
luma/app/components/TableOfContents.tsx
luma/app/components/Tabs.module.css
luma/app/components/Tabs.tsx
luma/app/components/TopNav.module.css
luma/app/components/TopNav.tsx
luma/app/components/VersionSelector.module.css
luma/app/components/VersionSelector.tsx
luma/app/components/index.js
luma/app/data/apis.json
luma/app/data/config.json
luma/app/data/search-index.json
luma/app/markdoc/nodes/fence.markdoc.ts
luma/app/markdoc/nodes/heading.markdoc.ts
luma/app/markdoc/nodes/index.ts
luma/app/markdoc/nodes/link.markdoc.ts
luma/app/markdoc/nodes/text.markdoc.ts
luma/app/markdoc/tags/callout.markdoc.ts
luma/app/markdoc/tags/index.ts
luma/app/markdoc/tags/tabs.markdoc.ts
luma/app/markdoc/utils.ts
luma/app/next-env.d.ts
luma/app/next.config.ts
luma/app/package-lock.json
luma/app/package.json
luma/app/pages/_app.tsx
luma/app/pages/_document.tsx
luma/app/pages/fonts/GeistMonoVF.woff
luma/app/pages/fonts/GeistVF.woff
luma/app/postcss.config.mjs
luma/app/public/default-favicon.ico
luma/app/public/file.svg
luma/app/public/globe.svg
luma/app/public/next.svg
luma/app/public/vercel.svg
luma/app/public/window.svg
luma/app/styles/globals.css
luma/app/styles/prism-theme.css
luma/app/tailwind.config.ts
luma/app/tsconfig.json
luma/app/types/config.tsx
luma/app/types.ts
luma/bootstrap.py
luma/config/__init__.py
luma/config/resolution.py
luma/config/resolved_config.py
luma_docs-0.0.14.dist-info/LICENSE
luma_docs-0.0.14.dist-info/METADATA
luma_docs-0.0.14.dist-info/WHEEL
luma_docs-0.0.14.dist-info/entry_points.txt
luma_docs-0.0.14.dist-info/RECORD
