Metadata-Version: 2.1
Name: luma-docs
Version: 0.0.14
Summary: 
License: Apache-2.0
Author: The Luma Team
Author-email: bveeramani@berkeley.edu
Requires-Python: >=3.10,<4.0
Classifier: License :: OSI Approved :: Apache Software License
Classifier: Programming Language :: Python :: 3
Classifier: Programming Language :: Python :: 3.10
Classifier: Programming Language :: Python :: 3.11
Classifier: Programming Language :: Python :: 3.12
Classifier: Programming Language :: Python :: 3.13
Requires-Dist: docstring-parser (>=0.16,<0.17)
Requires-Dist: docutils (>=0.21,<0.22)
Requires-Dist: keyring (>=25.5.0,<26.0.0)
Requires-Dist: pathspec (>=0.12.1,<0.13.0)
Requires-Dist: pydantic (>=2.10.3,<3.0.0)
Requires-Dist: python-frontmatter (>=1.1.0,<2.0.0)
Requires-Dist: pyyaml (>=6.0.2,<7.0.0)
Requires-Dist: requests (>=2.32.3,<3.0.0)
Requires-Dist: rich (>=13.9.4,<14.0.0)
Requires-Dist: typer (>=0.13.1,<0.14.0)
Requires-Dist: watchdog (>=6.0.0,<7.0.0)
